epicnumbers/__init__.py
epicnumbers/main.py
epicnumbers-1.1.0.dist-info/entry_points.txt
epicnumbers-1.1.0.dist-info/LICENSE
epicnumbers-1.1.0.dist-info/WHEEL
epicnumbers-1.1.0.dist-info/METADATA
epicnumbers-1.1.0.dist-info/RECORD
