Metadata-Version: 2.1
Name: epicnumbers
Version: 1.1.0
Summary: A tool to convert numbers into various other formats and different sized integers
Home-page: https://github.com/narhen/epicnumbers
License: MIT
Keywords: number,integer,conversion,cli
Author: Henrik Nårstad
Author-email: henriknaa@gmail.com
Requires-Python: >=3.7,<4.0
Classifier: License :: OSI Approved :: MIT License
Classifier: Programming Language :: Python :: 3
Classifier: Programming Language :: Python :: 3.7
Classifier: Programming Language :: Python :: 3.8
Classifier: Programming Language :: Python :: 3.9
Requires-Dist: importlib-metadata (>=3.4.0,<4.0.0); python_version < "3.8"
Requires-Dist: tabulate (>=0.8.8,<0.9.0)
Project-URL: Repository, https://github.com/narhen/epicnumbers
